PyFocus/__init__.py
PyFocus/log_config.py
PyFocus/plot.py
PyFocus/sim.py
PyFocus/custom_dataclasses/__init__.py
PyFocus/custom_dataclasses/custom_mask.py
PyFocus/custom_dataclasses/field_parameters.py
PyFocus/custom_dataclasses/interface_parameters.py
PyFocus/custom_dataclasses/mask.py
PyFocus/custom_typing/__init__.py
PyFocus/equations/__init__.py
PyFocus/equations/complex_quadrature.py
PyFocus/equations/coordinate_change.py
PyFocus/equations/gaussian_profile.py
PyFocus/equations/no_phase_mask.py
PyFocus/equations/normalize_intensity.py
PyFocus/equations/radial_simmetry.py
PyFocus/equations/tmm_core.py
PyFocus/equations/vortex_phase_mask.py
PyFocus/equations/helpers/__init__.py
PyFocus/model/__init__.py
PyFocus/model/main_calculation_handler.py
PyFocus/model/focus_field_calculators/__init__.py
PyFocus/model/focus_field_calculators/base.py
PyFocus/model/focus_field_calculators/custom_mask.py
PyFocus/model/focus_field_calculators/no_mask.py
PyFocus/model/focus_field_calculators/propagated_vortex_mask.py
PyFocus/model/focus_field_calculators/vortex_mask.py
PyFocus/model/focus_field_calculators/interface/__init__.py
PyFocus/model/focus_field_calculators/interface/interface.py
PyFocus/model/focus_field_calculators/interface/transfer matrix/__init__.py
PyFocus/model/focus_field_calculators/interface/transfer matrix/tmm_core.py
PyFocus/model/free_propagation_calculators/__init__.py
PyFocus/model/free_propagation_calculators/base.py
PyFocus/model/free_propagation_calculators/custom_mask.py
PyFocus/model/free_propagation_calculators/no_mask.py
PyFocus/model/free_propagation_calculators/vortex_mask.py
PyFocus/napari_adapter/__init__.py
PyFocus/napari_adapter/napari_adapter.py
PyFocus/plot_functions/__init__.py
PyFocus/plot_functions/plot_at_focus.py
PyFocus/plot_functions/plot_at_focus_3D.py
PyFocus/plot_functions/plot_objective_field.py
PyFocus/plot_functions/plot_polarization_elipses.py
PyFocus/user_interface/__init__.py
PyFocus/user_interface/front_end_ui.py
PyCustomFocus-3.4.0.dist-info/LICENCE.txt
PyCustomFocus-3.4.0.dist-info/METADATA
PyCustomFocus-3.4.0.dist-info/WHEEL
PyCustomFocus-3.4.0.dist-info/top_level.txt
PyCustomFocus-3.4.0.dist-info/RECORD
