Metadata-Version: 2.1
Name: PyCustomFocus
Version: 3.4.0
Summary: Full vectorial calculation of focused electromagnetic fields moduled by a custom phase mask
Home-page: https://github.com/fcaprile/PyFocus
Author: Caprile Fernando
Author-email: fcaprile@gmail.com
Classifier: Development Status :: 3 - Alpha
Classifier: Intended Audience :: Developers
Classifier: Topic :: Software Development :: Build Tools
Classifier: License :: OSI Approved :: MIT License
Classifier: Programming Language :: Python :: 3.9
Requires-Python: >=3.8
License-File: LICENCE.txt
